csum/__init__.py
csum/__main__.py
csum/argparsing.py
csum/checksums.py
csum-1.0.0.dist-info/LICENSE
csum-1.0.0.dist-info/METADATA
csum-1.0.0.dist-info/WHEEL
csum-1.0.0.dist-info/entry_points.txt
csum-1.0.0.dist-info/top_level.txt
csum-1.0.0.dist-info/RECORD
