Metadata-Version: 2.1
Name: csum
Version: 1.0.0
Summary: CLI for verifying checksums with the minimum effort.
Home-page: UNKNOWN
Author: Sam McCormack
Author-email: cabbagedevelopment@gmail.com
License: UNKNOWN
Project-URL: Source, https://github.com/CabbageDevelopment/csum
Keywords: cli tool path windows
Platform: UNKNOWN
Classifier: Intended Audience :: Developers
Classifier: License :: OSI Approved :: MIT License
Requires-Python: ~=3.6
